propertysync/__about__.py
propertysync/__init__.py
propertysync/api.py
propertysync/batch.py
propertysync/document.py
propertysync/search.py
propertysync/titlesearch_batch.py
propertysync-0.12.0.dist-info/METADATA
propertysync-0.12.0.dist-info/WHEEL
propertysync-0.12.0.dist-info/licenses/LICENSE
propertysync-0.12.0.dist-info/RECORD
