Metadata-Version: 2.3
Name: propertysync
Version: 0.12.0
Summary: A package for interacting with the PropertySync API.
Project-URL: Documentation, https://developer.propertysync.com/python/index.html
Author-email: Rob Martinson <rob@limelyte.com>
License: MIT
Classifier: Development Status :: 4 - Beta
Classifier: Programming Language :: Python
Classifier: Programming Language :: Python :: 3.7
Classifier: Programming Language :: Python :: 3.8
Classifier: Programming Language :: Python :: 3.9
Classifier: Programming Language :: Python :: 3.10
Classifier: Programming Language :: Python :: 3.11
Classifier: Programming Language :: Python :: Implementation :: CPython
Classifier: Programming Language :: Python :: Implementation :: PyPy
Requires-Python: >=3.7
Requires-Dist: jsonpath-ng
Requires-Dist: requests
